normative_diversity/__init__.py
normative_diversity/RADio/__init__.py
normative_diversity/RADio/distributions.py
normative_diversity/RADio/divergence.py
normative_diversity/RADio/functions.py
normative_diversity/RADio/metric.py
normative_diversity/RADio/visualize.py
normative_diversity-0.0.2.dist-info/LICENSE
normative_diversity-0.0.2.dist-info/METADATA
normative_diversity-0.0.2.dist-info/WHEEL
normative_diversity-0.0.2.dist-info/top_level.txt
normative_diversity-0.0.2.dist-info/RECORD
