Metadata-Version: 2.1
Name: normative_diversity
Version: 0.0.2
Summary: Package about normative diverity
Author-email: Sanne Vrijenhoek <s.vrijenhoek@uva.nl>
License: Apache License
Requires-Python: >=3.9
License-File: LICENSE
Requires-Dist: numpy<3.0,>2.0
Requires-Dist: scikit-learn==1.5.1
Requires-Dist: scipy==1.14.1
